custom_auth_user/__init__.py
custom_auth_user/admin.py
custom_auth_user/apps.py
custom_auth_user/models.py
custom_auth_user/auth_token/__init__.py
custom_auth_user/auth_token/admin.py
custom_auth_user/auth_token/authenticate_token.py
custom_auth_user/auth_token/authenticate_user.py
custom_auth_user/auth_token/decorators.py
custom_auth_user/auth_token/delete_token.py
custom_auth_user/auth_token/exceptions.py
custom_auth_user/auth_token/manager.py
custom_auth_user/auth_token/model.py
custom_auth_user/auth_token/store.py
custom_auth_user/auth_token/commands/__init__.py
custom_auth_user/auth_token/commands/authenticate_token_command.py
custom_auth_user/auth_token/commands/authenticate_user_command.py
custom_auth_user/auth_token/commands/create_auth_token_command.py
custom_auth_user/auth_token/commands/delete_token_command.py
custom_auth_user/auth_token/scripts/delete_expired_token.py
custom_auth_user/migrations/0001_initial.py
custom_auth_user/migrations/__init__.py
custom_auth_user/user/__init__.py
custom_auth_user/user/admin.py
custom_auth_user/user/exceptions.py
custom_auth_user/user/manager.py
custom_auth_user/user/model.py
custom_auth_user/user/registration.py
custom_auth_user/user/store.py
custom_auth_user/user/commands/__init__.py
custom_auth_user/user/commands/register_command.py
custom_auth_user/user/forms/__init__.py
custom_auth_user/user/forms/registration_form.py
django_custom_auth_user-0.1.2.dist-info/DESCRIPTION.rst
django_custom_auth_user-0.1.2.dist-info/LICENSE.txt
django_custom_auth_user-0.1.2.dist-info/METADATA
django_custom_auth_user-0.1.2.dist-info/RECORD
django_custom_auth_user-0.1.2.dist-info/WHEEL
django_custom_auth_user-0.1.2.dist-info/metadata.json
django_custom_auth_user-0.1.2.dist-info/top_level.txt
