Metadata-Version: 1.1
Name: django-custom-auth-user
Version: 0.1.2
Summary: Django custom user
Home-page: https://github.com/anthon-alindada/django_custom_auth_user
Author: Anthon Alindada
Author-email: anthon.alindada.435@gmail.com
License: MIT
Keywords: django custom auth user
Platform: UNKNOWN
Classifier: Development Status :: 3 - Alpha
Classifier: Framework :: Django
Classifier: Framework :: Django :: 1.10
Classifier: Intended Audience :: Developers
Classifier: License :: OSI Approved :: BSD License
Classifier: Natural Language :: English
Classifier: Programming Language :: Python :: 2
Classifier: Programming Language :: Python :: 2.7
Classifier: Programming Language :: Python :: 3
Classifier: Programming Language :: Python :: 3.4
Classifier: Programming Language :: Python :: 3.5
